Workbook

Sheet Roadmap
A1: Month | B1: Focus | C1: Kya seekhna hai | D1: Tools | E1: Month ke end tak goal
A2: Month 1 | B2: Excel + SQL basics | C2: Formulas, Lookups, Pivot Tables, Charts, Data Cleaning, SQL SELECT/WHERE/GROUP BY | D2: Excel, SQLite ya MySQL/PostgreSQL | E2: Ek clean Excel dashboard + 20 SQL questions solve
A3: Month 2 | B3: SQL (advanced) | C3: JOINs, Subqueries, CTEs, CASE WHEN, Window Functions, Date functions | D3: PostgreSQL / MySQL, LeetCode SQL, HackerRank | E3: SQL project + 50 practice questions
A4: Month 3 | B4: Python for Data | C4: Pandas, NumPy, Data Cleaning, EDA, Matplotlib/Seaborn | D4: Jupyter Notebook / Google Colab, Kaggle | E4: Ek full Python analysis project (Kaggle dataset)
A5: Month 4 | B5: Power BI (ya Tableau) | C5: Power Query, Data Model, DAX basics, Dashboard design | D5: Power BI Desktop (free) | E5: Ek professional dashboard, publish ya screenshots
A6: Month 5 | B6: Statistics + Business sense | C6: Mean/Median/Std, Correlation, Hypothesis testing, A/B testing, KPIs, Storytelling | D6: Python, Excel, Khan Academy | E6: Final end-to-end project (SQL + Python + Power BI)
A7: Month 6 | B7: Job preparation | C7: Resume, LinkedIn, GitHub portfolio, Interview prep, Mock interviews, Applications | D7: LinkedIn, Naukri, Internshala, Indeed | E7: Roz applications + interviews shuru
A9: Rules:
A10: 1. Roz kam se kam 2-3 ghante practice karo (weekly 15-20 ghante). Sirf video dekhna kaafi nahi hai.
A11: 2. 6 mahine tak path mat badlo. Month 3 par check karo ki data ka kaam pasand aa raha hai ya nahi.
A12: 3. AI ka use samajhne aur debug karne ke liye karo, lekin code khud likhkar practice karo.
A13: 4. Har project GitHub par daalo aur likho: problem kya thi, kya kiya, kya insight mili.

Sheet Weekly Plan
A1: Week | B1: Month | C1: Topic area | D1: Kya seekhna hai | E1: Practice / Target | F1: Hours | G1: Status
A2: 1 | B2: Month 1 | C2: Excel | D2: Excel basics: formatting, sort, filter, SUM/AVERAGE/COUNT/IF, absolute reference | E2: Ek sales dataset download karke clean aur format karo | F2: 15 | G2: Done
A3: 2 | B3: Month 1 | C3: Excel | D3: VLOOKUP / INDEX-MATCH, SUMIFS, COUNTIFS, text aur date functions | E3: 10 lookup + conditional sum problems solve karo | F3: 15 | G3: Done
A4: 3 | B4: Month 1 | C4: Excel | D4: Pivot tables, charts, remove duplicates, text to columns, conditional formatting | E4: Ek 1-page Excel dashboard banao | F4: 15 | G4: Done
A5: 4 | B5: Month 1 | C5: SQL | D5: Database kya hai, SELECT, WHERE, ORDER BY, LIMIT, COUNT/SUM/AVG | E5: SQLBolt ke saare lessons + 15 easy questions | F5: 15 | G5: Done
A6: 5 | B6: Month 2 | C6: SQL | D6: GROUP BY, HAVING, INNER/LEFT JOIN, multiple tables | E6: 20 questions (JOINs par focus) | F6: 15 | G6: Not Started
A7: 6 | B7: Month 2 | C7: SQL | D7: Subqueries, CTEs, CASE WHEN, string aur date functions | E7: 20 medium questions | F7: 15 | G7: Not Started
A8: 7 | B8: Month 2 | C8: SQL | D8: Window functions: ROW_NUMBER, RANK, LAG/LEAD, running total | E8: 15 window function questions | F8: 15 | G8: Not Started
A9: 8 | B9: Month 2 | C9: SQL | D9: SQL project: kisi dataset par 10 business sawal SQL se solve karo | E9: GitHub par SQL project upload karo | F9: 18 | G9: Not Started
A10: 9 | B10: Month 3 | C10: Python | D10: Python refresh (list, dict, loops, functions) + Pandas basics: DataFrame, read_csv | E10: Kaggle Learn: Python + Pandas course | F10: 15 | G10: Done
A11: 10 | B11: Month 3 | C11: Python | D11: Pandas: filter, groupby, merge, missing values, duplicates, data types | E11: Ek messy dataset ko clean karo | F11: 15 | G11: Not Started
A12: 11 | B12: Month 3 | C12: Python | D12: NumPy basics, EDA, Matplotlib aur Seaborn charts | E12: Ek dataset ke 8-10 charts banao aur insights likho | F12: 15 | G12: Not Started
A13: 12 | B13: Month 3 | C13: Python | D13: Python project: end-to-end analysis (clean, explore, visualize, conclude) | E13: Jupyter notebook GitHub par upload karo | F13: 18 | G13: Not Started
... A25: 24 | B25: Month 6 | C25: Job | D25: Applications + follow-up, internship/freelance, weak topics revise | E25: Interviews attend karo aur feedback se seekho | F25: 15 | G25: Not Started

Sheet Progress
A1: Month | B1: Total weeks | C1: Weeks done | D1: Progress %
A2: Month 1 | B2: =COUNTIF('Weekly Plan'!$B$2:$B$25,A2) -> 4 | C2: =COUNTIFS('Weekly Plan'!$B$2:$B$25,A2,'Weekly Plan'!$G$2:$G$25,"Done") -> 4 | D2: =IF(B2=0,0,C2/B2) -> 1
A3: Month 2 | B3: =COUNTIF('Weekly Plan'!$B$2:$B$25,A3) -> 4 | C3: =COUNTIFS('Weekly Plan'!$B$2:$B$25,A3,'Weekly Plan'!$G$2:$G$25,"Done") -> 0 | D3: =IF(B3=0,0,C3/B3) -> 0
A4: Month 3 | B4: =COUNTIF('Weekly Plan'!$B$2:$B$25,A4) -> 4 | C4: =COUNTIFS('Weekly Plan'!$B$2:$B$25,A4,'Weekly Plan'!$G$2:$G$25,"Done") -> 1 | D4: =IF(B4=0,0,C4/B4) -> 0.25
A5: Month 4 | B5: =COUNTIF('Weekly Plan'!$B$2:$B$25,A5) -> 4 | C5: =COUNTIFS('Weekly Plan'!$B$2:$B$25,A5,'Weekly Plan'!$G$2:$G$25,"Done") -> 2 | D5: =IF(B5=0,0,C5/B5) -> 0.5
A6: Month 5 | B6: =COUNTIF('Weekly Plan'!$B$2:$B$25,A6) -> 4 | C6: =COUNTIFS('Weekly Plan'!$B$2:$B$25,A6,'Weekly Plan'!$G$2:$G$25,"Done") -> 0 | D6: =IF(B6=0,0,C6/B6) -> 0
A7: Month 6 | B7: =COUNTIF('Weekly Plan'!$B$2:$B$25,A7) -> 4 | C7: =COUNTIFS('Weekly Plan'!$B$2:$B$25,A7,'Weekly Plan'!$G$2:$G$25,"Done") -> 0 | D7: =IF(B7=0,0,C7/B7) -> 0
A8: Total | B8: =SUM(B2:B7) -> 24 | C8: =SUM(C2:C7) -> 7 | D8: =IF(B8=0,0,C8/B8) -> 0.29166667
A10: Kaise use kare: 'Weekly Plan' sheet me Status column ko Done / In Progress / Not Started karo. Yahan progress apne aap update hoga.

Sheet Projects
A1: Project | B1: Kab | C1: Dataset idea | D1: Skills use hongi | E1: Kaunsa sawal solve karna hai
A2: 1. Excel Sales Dashboard | B2: Month 1 | C2: Superstore Sales (Kaggle) | D2: Pivot tables, charts, slicers | E2: Kaunsa region/product sabse zyada profit deta hai? Kahan loss hai?
A3: 2. SQL Business Analysis | B3: Month 2 | C3: Olist E-commerce ya Chinook / Northwind DB | D3: JOINs, CTEs, window functions | E3: Top customers, monthly revenue trend, repeat customer rate
A4: 3. Python EDA Project | B4: Month 3 | C4: Kaggle: Titanic nahi, kuch real jaise Netflix, Zomato ya Airbnb dataset | D4: Pandas, cleaning, Seaborn charts | E4: Kya patterns hain? Business ko kya recommend karoge?
A5: 4. Power BI Dashboard | B5: Month 4 | C5: HR Attrition ya Sales dataset | D5: Power Query, DAX, KPI design | E5: Employees kyun chhod rahe hain? Kis department me zyada?
A6: 5. Final End-to-End Case Study | B6: Month 5 | C6: Koi bhi real dataset (data.gov.in, Kaggle) | D6: SQL + Python + Power BI | E6: Ek business problem choose karo, poora analysis karo aur report likho
A8: Tip: Har project ke README me likho: Problem, Data, Steps, Insights, Recommendation. Interviewer yahi padhta hai.

Sheet Resources
A1: Topic | B1: Kahan se seekhe | C1: Cost
A2: Excel | B2: Chandoo.org, ExcelIsFun (YouTube), Microsoft Excel help | C2: Free
A3: SQL | B3: SQLBolt, Mode SQL Tutorial, W3Schools SQL, LeetCode / HackerRank SQL practice | C3: Free
A4: Python for Data | B4: Kaggle Learn (Python, Pandas, Data Visualization), freeCodeCamp Data Analysis with Python | C4: Free
A5: Power BI | B5: Microsoft Learn (PL-300 learning path), Guy in a Cube (YouTube) | C5: Free
A6: Statistics | B6: Khan Academy Statistics and Probability | C6: Free
A7: Datasets | B7: Kaggle Datasets, data.gov.in, Google Dataset Search | C7: Free
A8: Job search | B8: LinkedIn, Naukri, Internshala, Indeed, company career pages | C8: Free
A9: Portfolio | B9: GitHub (projects), LinkedIn (posts), Kaggle profile | C9: Free

Sheet Interview Prep
A1: Area | B1: Common questions | C1: Tip
A2: Excel | B2: VLOOKUP aur INDEX-MATCH me kya difference hai? Pivot table kab use karte ho? | C2: Live example ke saath explain karna seekho.
A3: SQL | B3: INNER vs LEFT JOIN? WHERE vs HAVING? Second highest salary nikalo. Running total kaise nikalte ho? | C3: Sabse zyada poochha jaata hai. Roz practice karo.
A4: Python | B4: Pandas me missing values kaise handle karte ho? merge vs join? groupby kaise kaam karta hai? | C4: Apne project ke example se jawab do.
A5: Power BI | B5: DAX me calculated column vs measure? Relationships kaise banate ho? Dashboard kaise design kiya? | C5: Apna dashboard dikhane ke liye ready raho.
A6: Statistics | B6: Mean vs median kab? Correlation aur causation me difference? A/B test kya hai? | C6: Simple language me samjhao.
A7: Business case | B7: Sales gir rahi hai to kaise analyze karoge? Kaunse KPIs dekhoge? | C7: Pehle sawal samjho, phir data aur steps batao.
A8: Behavioral | B8: Apne project ke baare me batao. Koi mushkil problem jo solve ki. | C8: STAR format: Situation, Task, Action, Result.
